api_estcube_helpers/__init__.py
api_estcube_helpers/custom_logging.py
api_estcube_helpers-0.0.1.dist-info/LICENSE
api_estcube_helpers-0.0.1.dist-info/METADATA
api_estcube_helpers-0.0.1.dist-info/WHEEL
api_estcube_helpers-0.0.1.dist-info/top_level.txt
api_estcube_helpers-0.0.1.dist-info/RECORD
