Metadata-Version: 2.1
Name: api-estcube-helpers
Version: 0.0.1
Summary: Helper functions for ESTCube Mission Control
Home-page: https://github.com/estcube/api-estcube-helpers
Author: Umesh .A Bhat
Author-email: umesh.bhat@estcube.eu
License: UNKNOWN
Platform: UNKNOWN
Classifier: Programming Language :: Python :: 3
Classifier: License :: OSI Approved :: MIT License
Classifier: Operating System :: OS Independent
Requires-Python: >=3.6
